ipdata/__init__.py
ipdata/cli.py
ipdata/codes.py
ipdata/geofeeds.py
ipdata/ipdata.py
ipdata/iptrie.py
ipdata/lolcat.py
ipdata/test_geofeeds.py
ipdata/test_ipdata.py
ipdata/test_iptrie.py
ipdata-4.0.8.dist-info/licenses/LICENSE
ipdata-4.0.8.dist-info/METADATA
ipdata-4.0.8.dist-info/WHEEL
ipdata-4.0.8.dist-info/entry_points.txt
ipdata-4.0.8.dist-info/top_level.txt
ipdata-4.0.8.dist-info/RECORD
