Metadata-Version: 2.4
Name: ipdata
Version: 4.0.8
Summary: This is the official IPData client library for Python
Home-page: https://github.com/ipdata/python
Author: Jonathan Kosgei
Author-email: jonathan@ipdata.co
Project-URL: Bug Tracker, https://github.com/ipdata/python/issues
Classifier: Programming Language :: Python :: 3.9
Classifier: Programming Language :: Python :: 3.10
Classifier: Programming Language :: Python :: 3.11
Classifier: Programming Language :: Python :: 3.12
Classifier: Programming Language :: Python :: 3.13
Classifier: License :: OSI Approved :: MIT License
Classifier: Operating System :: OS Independent
Requires-Python: >=3.9
License-File: LICENSE
Requires-Dist: requests
Requires-Dist: rich
Requires-Dist: click
Requires-Dist: click_default_group
Requires-Dist: pyperclip
Requires-Dist: pytest
Requires-Dist: hypothesis
Requires-Dist: python-dotenv
Requires-Dist: pytricia
Dynamic: license-file
